seleccion_voluntariado_2023/__init__.py
seleccion_voluntariado_2023/transformations.py
seleccion_voluntariado_2023-0.4.0.dist-info/LICENSE
seleccion_voluntariado_2023-0.4.0.dist-info/WHEEL
seleccion_voluntariado_2023-0.4.0.dist-info/METADATA
seleccion_voluntariado_2023-0.4.0.dist-info/RECORD
