Metadata-Version: 2.1
Name: seleccion_voluntariado_2023
Version: 0.4.0
Summary: An example of a Python module
Home-page: https://github.com/IslasGECI/seleccion_voluntariado_2023
Author: Ciencia de Datos • GECI
Author-email: ciencia.datos@islas.org.mx
Requires-Python: >=3.9
Classifier: License :: OSI Approved :: GNU General Public License v3 or later (GPLv3+)
